replikant/__init__.py
replikant/__main__.py
replikant/database.py
replikant/extensions.py
replikant/main.py
replikant/utils.py
replikant/activities/auth_by_invitation/__init__.py
replikant/activities/auth_by_invitation/model.py
replikant/activities/auth_by_invitation/provider.py
replikant/activities/auth_by_invitation/templates/default.tpl
replikant/activities/auth_by_invitation/templates/legal.tpl
replikant/activities/auth_by_invitation/templates/admin/config.tpl
replikant/activities/auth_by_invitation/templates/admin/panel.tpl
replikant/activities/auth_by_invitation/templates/admin/pending.tpl
replikant/activities/auth_by_invitation/templates/admin/send_invitation.tpl
replikant/activities/email_auth/__init__.py
replikant/activities/email_auth/model.py
replikant/activities/email_auth/provider.py
replikant/activities/email_auth/templates/default.tpl
replikant/activities/form/__init__.py
replikant/activities/form/model/Form.py
replikant/activities/form/model/__init__.py
replikant/activities/form/templates/dynamic_form.tpl
replikant/activities/page/__init__.py
replikant/activities/page/templates/default.tpl
replikant/activities/prolific_auth/__init__.py
replikant/activities/prolific_auth/model.py
replikant/activities/prolific_auth/provider.py
replikant/activities/prolific_auth/templates/default.tpl
replikant/activities/section_summary/__init__.py
replikant/activities/section_summary/templates/default.tpl
replikant/activities/task/__init__.py
replikant/activities/task/model.py
replikant/activities/task/src/__init__.py
replikant/activities/task/src/system.py
replikant/activities/task/src/task.py
replikant/activities/task/src/selection_strategy/__init__.py
replikant/activities/task/src/selection_strategy/core.py
replikant/activities/task/src/selection_strategy/latin_square.py
replikant/activities/task/src/selection_strategy/least_seen.py
replikant/activities/task/templates/mushra.tpl
replikant/activities/task/templates/rpt.tpl
replikant-0.0.3.dist-info/licenses/LICENSE
replikant-0.0.3.dist-info/METADATA
replikant-0.0.3.dist-info/WHEEL
replikant-0.0.3.dist-info/entry_points.txt
replikant-0.0.3.dist-info/top_level.txt
replikant-0.0.3.dist-info/RECORD
