Metadata-Version: 2.4
Name: replikant
Version: 0.0.3
Summary: A flexible toolkit to enable replicable subjective evaluations
Author-email: Sébastien Le Maguer <sebastien.lemaguer@helsinki.fi>
Maintainer-email: Sébastien Le Maguer <sebastien.lemaguer@helsinki.fi>
License-Expression: EUPL-1.2
Project-URL: Homepage, https://github.com/seblemaguer/replikant
Project-URL: Issues, https://github.com/seblemaguer/replikant/issues
Project-URL: git, https://github.com/seblemaguer/replikant.git
Keywords: subjective evaluation,survey,flexible,replicability,flask,jinj2
Classifier: Development Status :: 4 - Beta
Classifier: Intended Audience :: Science/Research
Classifier: Programming Language :: Python :: 3 :: Only
Classifier: Programming Language :: Python :: 3.11
Classifier: Programming Language :: Python :: 3.12
Classifier: Environment :: Web Environment
Classifier: Framework :: Flask
Requires-Python: >=3.11
License-File: LICENSE
Requires-Dist: cachelib>=0.7
Requires-Dist: click>=8.1.3
Requires-Dist: Flask>=2.1.2
Requires-Dist: Flask-Session>=0.4
Requires-Dist: Flask-SQLAlchemy>=2.5.1
Requires-Dist: gevent
Requires-Dist: greenlet>=1.1.2
Requires-Dist: gunicorn
Requires-Dist: importlib-metadata>=4.11.4
Requires-Dist: itsdangerous>=2.1.2
Requires-Dist: Jinja2>=3.1.2
Requires-Dist: MarkupSafe>=2.1.1
Requires-Dist: pandas>=2.2.1
Requires-Dist: PyYAML>=6
Requires-Dist: SQLAlchemy>=2.0.27
Requires-Dist: Werkzeug>=2.1.2
Requires-Dist: zipp>=3.8
Provides-Extra: dev
Requires-Dist: pre-commit; extra == "dev"
Requires-Dist: black; extra == "dev"
Requires-Dist: basedpyright; extra == "dev"
Provides-Extra: test
Requires-Dist: selenium; extra == "test"
Dynamic: license-file
